markten/__action_session.py
markten/__cli.py
markten/__consts.py
markten/__context.py
markten/__init__.py
markten/__main__.py
markten/__recipe/__init__.py
markten/__recipe/parameters.py
markten/__recipe/recipe.py
markten/__recipe/runner.py
markten/__recipe/step.py
markten/__utils.py
markten/actions/__action.py
markten/actions/__email.py
markten/actions/__fs.py
markten/actions/__git.py
markten/actions/__gitlab.py
markten/actions/__init__.py
markten/actions/__misc.py
markten/actions/__process.py
markten/actions/__time.py
markten/actions/__webbrowser.py
markten/actions/editor/__init__.py
markten/actions/editor/__vs_code.py
markten/actions/editor/__zed.py
markten/actions/email.py
markten/actions/fs.py
markten/actions/git.py
markten/actions/process.py
markten/actions/time.py
markten/actions/webbrowser.py
markten/more_itertools.py
markten/parameters/__fs.py
markten/parameters/__init__.py
markten/parameters/__io.py
markten/parameters/__object.py
markten/py.typed
markten-1.3.4.dist-info/WHEEL
markten-1.3.4.dist-info/entry_points.txt
markten-1.3.4.dist-info/METADATA
markten-1.3.4.dist-info/RECORD
