Metadata-Version: 2.4
Name: markten
Version: 1.3.4
Summary: Assess your students' work with all of the delight and none of the tedium
Keywords: marking,auto-marker,automation,xmark,imark,mark,ten
Author: Maddy Guthridge
Author-email: Maddy Guthridge <hello@maddyguthridge.com>
License-Expression: MIT
Classifier: Programming Language :: Python :: 3
Classifier: Environment :: Console
Classifier: Intended Audience :: Developers
Classifier: Intended Audience :: Education
Classifier: License :: OSI Approved :: MIT License
Classifier: Operating System :: OS Independent
Classifier: Development Status :: 5 - Production/Stable
Classifier: Topic :: Education
Classifier: Topic :: Education :: Testing
Classifier: Typing :: Typed
Requires-Dist: rich>=14,<15
Requires-Dist: click>=8.3,<9
Requires-Dist: platformdirs>=4.3.6,<5.0.0
Requires-Dist: aiosqlite>=0.21.0,<0.22.0
Requires-Dist: humanize>=4.12.2,<5.0.0
Requires-Dist: aiofiles>=24.1.0,<25.0.0
Requires-Dist: pyreadline3>=3.5.4 ; sys_platform == 'win32'
Requires-Dist: typing-extensions>=4.12.2
Requires-Python: >=3.11
Project-URL: Bug Tracker, https://github.com/COMP1010UNSW/Markten/issues
Project-URL: repository, https://github.com/COMP1010UNSW/Markten
